loteria_caixa/__init__.py
loteria_caixa-0.0.5.dist-info/LICENSE
loteria_caixa-0.0.5.dist-info/METADATA
loteria_caixa-0.0.5.dist-info/WHEEL
loteria_caixa-0.0.5.dist-info/top_level.txt
loteria_caixa-0.0.5.dist-info/RECORD
