Metadata-Version: 2.1
Name: loteria-caixa
Version: 0.0.5
Summary: Um simples e fácil meio de receber dados de sorteio das loterias caixa
Home-page: https://github.com/claudiotorresarbe/loteria_caixa
Author: Claudio Torres Arbe
Author-email: claudiotarbe@gmail.com
License: UNKNOWN
Platform: UNKNOWN
Classifier: Programming Language :: Python :: 3.8
Classifier: License :: OSI Approved :: MIT License
Classifier: Operating System :: OS Independent
Requires-Python: >=3.6
License-File: LICENSE
Requires-Dist: requests (==2.25.1)
